{
    "+": "UA-EBERON",
    "@": "Shifter",
    "ability scores": {
        "+": 0,
        "cha": 0,
        "con": 0,
        "dex": 1,
        "int": 0,
        "str": 0,
        "wis": 0
    },
    "description": "Your cliffwalk heritage grants you the agility of a mountain goat.",
    "name": "Cliffwalk Shifter",
    "traits": [
        "Shifting Feature"
    ],
    "traits-data": {
        "Shifting Feature": [
            "While shifting you gain a climb speed of 30 feet."
        ]
    }
}
