{
    "+": "FREE",
    "ability scores": {
        "cha": 7,
        "con": 10,
        "dex": 15,
        "int": 3,
        "str": 14,
        "wis": 14
    },
    "actions": [
        [
            "Bite",
            "*Melee Weapon Attack:* +4 to hit, reach 5 ft., one target. *Hit:* 5 (1d6 + 2) piercing damage."
        ],
        [
            "Claw",
            "*Melee Weapon Attack:* +4 to hit, reach 5 ft., one target. *Hit:* 4 (1d4 + 2) slashing damage."
        ]
    ],
    "alignment": "unaligned",
    "armor class": "12",
    "experience": 50,
    "hit points": "13 (3d8)",
    "name": "Panther",
    "size": "Medium",
    "skills": {
        "Perception": 4,
        "Stealth": 6
    },
    "speed": [
        "50 ft.",
        "climb 40 ft."
    ],
    "traits": [
        [
            "Keen Smell",
            "The panther has advantage on Wisdom (Perception) checks that rely on smell."
        ],
        [
            "Pounce",
            "If the panther moves at least 20 feet straight toward a creature and then hits it with a claw attack on the same turn, that target must succeed on a DC 12 Strength saving throw or be knocked prone. If the target is prone, the panther can make one bite attack against it as a bonus action."
        ]
    ],
    "type": "beast"
}